[
  {
    "iteration": 1,
    "iteration_start": "2026-02-20T05:12:53.062751Z",
    "iteration_end": "2026-02-20T05:13:11.727400Z",
    "iteration_duration_seconds": 18.664984374998312,
    "sysml_path": "/Users/chancelavoie/Desktop/AI_AGENT_Benchmarking_Compiler_in_Loop/api_loop/runs/designbench_refine_api_loop/147/20260220-001252/iteration_01.sysml",
    "prompt_path": "/Users/chancelavoie/Desktop/AI_AGENT_Benchmarking_Compiler_in_Loop/api_loop/runs/designbench_refine_api_loop/147/20260220-001252/iteration_01_prompt.txt",
    "response_path": "/Users/chancelavoie/Desktop/AI_AGENT_Benchmarking_Compiler_in_Loop/api_loop/runs/designbench_refine_api_loop/147/20260220-001252/iteration_01_response.json",
    "success": true,
    "compiler_stdout": "Checks passed!",
    "compiler_stderr": "iteration_01.sysml:20:15: \u001b[38;2;204;204;057mwarning\u001b[0m (namespace-distinguishability): Member name 'name' shadows AlloySystem::Material::name\n\u2502   20 |     attribute name = \"Iron\";\n\u2502      |               \u001b[38;2;204;204;057m^^^^\u001b[0m\n\u2514\u2500\u2500 iteration_01.sysml:5:15: \u001b[38;2;255;255;255mnote\u001b[0m: Inherited from here\n    \u2514\u2500\u2500 iteration_01.sysml:19:15: \u001b[38;2;255;255;255mnote\u001b[0m: Because AlloySystem::Material is specialized through FeatureTyping\n\niteration_01.sysml:21:15: \u001b[38;2;204;204;057mwarning\u001b[0m (namespace-distinguishability): Member name 'atomicMass' shadows AlloySystem::Material::atomicMass\n\u2502   21 |     attribute atomicMass = 55.845;\n\u2502      |               \u001b[38;2;204;204;057m^^^^^^^^^^\u001b[0m\n\u2514\u2500\u2500 iteration_01.sysml:6:15: \u001b[38;2;255;255;255mnote\u001b[0m: Inherited from here\n    \u2514\u2500\u2500 iteration_01.sysml:19:15: \u001b[38;2;255;255;255mnote\u001b[0m: Because AlloySystem::Material is specialized through FeatureTyping\n\niteration_01.sysml:25:15: \u001b[38;2;204;204;057mwarning\u001b[0m (namespace-distinguishability): Member name 'name' shadows AlloySystem::Material::name\n\u2502   25 |     attribute name = \"Carbon\";\n\u2502      |               \u001b[38;2;204;204;057m^^^^\u001b[0m\n\u2514\u2500\u2500 iteration_01.sysml:5:15: \u001b[38;2;255;255;255mnote\u001b[0m: Inherited from here\n    \u2514\u2500\u2500 iteration_01.sysml:24:17: \u001b[38;2;255;255;255mnote\u001b[0m: Because AlloySystem::Material is specialized through FeatureTyping\n\niteration_01.sysml:26:15: \u001b[38;2;204;204;057mwarning\u001b[0m (namespace-distinguishability): Member name 'atomicMass' shadows AlloySystem::Material::atomicMass\n\u2502   26 |     attribute atomicMass = 12.011;\n\u2502      |               \u001b[38;2;204;204;057m^^^^^^^^^^\u001b[0m\n\u2514\u2500\u2500 iteration_01.sysml:6:15: \u001b[38;2;255;255;255mnote\u001b[0m: Inherited from here\n    \u2514\u2500\u2500 iteration_01.sysml:24:17: \u001b[38;2;255;255;255mnote\u001b[0m: Because AlloySystem::Material is specialized through FeatureTyping\n\niteration_01.sysml:30:15: \u001b[38;2;204;204;057mwarning\u001b[0m (namespace-distinguishability): Member name 'name' shadows AlloySystem::Material::name\n\u2502   30 |     attribute name = \"Manganese\";\n\u2502      |               \u001b[38;2;204;204;057m^^^^\u001b[0m\n\u2514\u2500\u2500 iteration_01.sysml:5:15: \u001b[38;2;255;255;255mnote\u001b[0m: Inherited from here\n    \u2514\u2500\u2500 iteration_01.sysml:29:20: \u001b[38;2;255;255;255mnote\u001b[0m: Because AlloySystem::Material is specialized through FeatureTyping\n\niteration_01.sysml:31:15: \u001b[38;2;204;204;057mwarning\u001b[0m (namespace-distinguishability): Member name 'atomicMass' shadows AlloySystem::Material::atomicMass\n\u2502   31 |     attribute atomicMass = 54.938;\n\u2502      |               \u001b[38;2;204;204;057m^^^^^^^^^^\u001b[0m\n\u2514\u2500\u2500 iteration_01.sysml:6:15: \u001b[38;2;255;255;255mnote\u001b[0m: Inherited from here\n    \u2514\u2500\u2500 iteration_01.sysml:29:20: \u001b[38;2;255;255;255mnote\u001b[0m: Because AlloySystem::Material is specialized through FeatureTyping\n\niteration_01.sysml:35:15: \u001b[38;2;204;204;057mwarning\u001b[0m (namespace-distinguishability): Member name 'tensileStrength' shadows AlloySystem::Alloy::tensileStrength\n\u2502   35 |     attribute tensileStrength = 980;\n\u2502      |               \u001b[38;2;204;204;057m^^^^^^^^^^^^^^^\u001b[0m\n\u2514\u2500\u2500 iteration_01.sysml:16:15: \u001b[38;2;255;255;255mnote\u001b[0m: Inherited from here\n    \u2514\u2500\u2500 iteration_01.sysml:34:19: \u001b[38;2;255;255;255mnote\u001b[0m: Because AlloySystem::Alloy is specialized through FeatureTyping\n\niteration_01.sysml:37:12: \u001b[38;2;204;204;057mwarning\u001b[0m (namespace-distinguishability): Member name 'material' shadows AlloySystem::Component::material\n\u2502   37 |       part material = iron;\n\u2502      |            \u001b[38;2;204;204;057m^^^^^^^^\u001b[0m\n\u2514\u2500\u2500 iteration_01.sysml:10:10: \u001b[38;2;255;255;255mnote\u001b[0m: Inherited from here\n    \u2514\u2500\u2500 iteration_01.sysml:36:21: \u001b[38;2;255;255;255mnote\u001b[0m: Because AlloySystem::Component is specialized through FeatureTyping\n\niteration_01.sysml:38:17: \u001b[38;2;204;204;057mwarning\u001b[0m (namespace-distinguishability): Member name 'massFraction' shadows AlloySystem::Component::massFraction\n\u2502   38 |       attribute massFraction = 0.98;\n\u2502      |                 \u001b[38;2;204;204;057m^^^^^^^^^^^^\u001b[0m\n\u2514\u2500\u2500 iteration_01.sysml:11:15: \u001b[38;2;255;255;255mnote\u001b[0m: Inherited from here\n    \u2514\u2500\u2500 iteration_01.sysml:36:21: \u001b[38;2;255;255;255mnote\u001b[0m: Because AlloySystem::Component is specialized through FeatureTyping\n\niteration_01.sysml:41:12: \u001b[38;2;204;204;057mwarning\u001b[0m (namespace-distinguishability): Member name 'material' shadows AlloySystem::Component::material\n\u2502   41 |       part material = carbon;\n\u2502      |            \u001b[38;2;204;204;057m^^^^^^^^\u001b[0m\n\u2514\u2500\u2500 iteration_01.sysml:10:10: \u001b[38;2;255;255;255mnote\u001b[0m: Inherited from here\n    \u2514\u2500\u2500 iteration_01.sysml:40:23: \u001b[38;2;255;255;255mnote\u001b[0m: Because AlloySystem::Component is specialized through FeatureTyping\n\niteration_01.sysml:42:17: \u001b[38;2;204;204;057mwarning\u001b[0m (namespace-distinguishability): Member name 'massFraction' shadows AlloySystem::Component::massFraction\n\u2502   42 |       attribute massFraction = 0.02;\n\u2502      |                 \u001b[38;2;204;204;057m^^^^^^^^^^^^\u001b[0m\n\u2514\u2500\u2500 iteration_01.sysml:11:15: \u001b[38;2;255;255;255mnote\u001b[0m: Inherited from here\n    \u2514\u2500\u2500 iteration_01.sysml:40:23: \u001b[38;2;255;255;255mnote\u001b[0m: Because AlloySystem::Component is specialized through FeatureTyping",
    "return_code": 0,
    "tokens_used_this_iter": {
      "input_tokens": 467,
      "output_tokens": 1091,
      "total_tokens": 1558
    },
    "tokens_used_total": 1558
  }
]